voltorb/__init__.py
voltorb/_patches.py
voltorb/_version.py
voltorb/api.py
voltorb/auth.py
voltorb/exceptions.py
voltorb/middlewares.py
voltorb/schemas.py
voltorb/serde.py
voltorb/typing.py
voltorb-0.1.0.dist-info/LICENSE.txt
voltorb-0.1.0.dist-info/METADATA
voltorb-0.1.0.dist-info/WHEEL
voltorb-0.1.0.dist-info/top_level.txt
voltorb-0.1.0.dist-info/RECORD
