Metadata-Version: 2.1
Name: voltorb
Version: 0.1.0
Summary: A simple unofficial Electricity Maps client
Author: amv213
Maintainer: avm213
Classifier: Development Status :: 1 - Planning
Classifier: Intended Audience :: Developers
Classifier: License :: OSI Approved :: MIT License
Classifier: Natural Language :: English
Classifier: Operating System :: OS Independent
Classifier: Programming Language :: Python
Classifier: Programming Language :: Python :: 3 :: Only
Classifier: Programming Language :: Python :: 3.10
Classifier: Programming Language :: Python :: 3.11
Classifier: Topic :: Utilities
Classifier: Typing :: Typed
Requires-Python: >=3.10
License-File: LICENSE.txt
Requires-Dist: attrs
Requires-Dist: cattrs
Requires-Dist: gentools
Requires-Dist: snug
Requires-Dist: typing-extensions
Provides-Extra: dev
Requires-Dist: nox >=2024.03.02 ; extra == 'dev'
Requires-Dist: pre-commit ; extra == 'dev'
Provides-Extra: tests
Requires-Dist: coverage[toml] ; extra == 'tests'
Requires-Dist: pytest ; extra == 'tests'
